LICENSE.txt
README.md
setup.cfg
setup.py
pysvl/__init__.py
pysvl/main.py
pysvl/realtime.py
pysvl/vehicle.py
pysvl.egg-info/PKG-INFO
pysvl.egg-info/SOURCES.txt
pysvl.egg-info/dependency_links.txt
pysvl.egg-info/requires.txt
pysvl.egg-info/top_level.txt