Metadata-Version: 2.1
Name: pysvl
Version: 1.0.0
Summary: PySVL is a python library for space vehicles, rockets and satellite for their designing, calculating their path, their orbit and more
Home-page: https://github.com/InfinityScienceWorks/pysvl
Download-URL: https://github.com/InfinityScienceWorks/pysvl/archive/refs/tags/python.tar.gz
Author: InfinityScienceWorks
Author-email: infinity.science.works@proton.me
License: MIT
Keywords: python,rocket,rocket calculation,projectile calculating,pysvl,PySVL,space vehicle
Classifier: Development Status :: 3 - Alpha
Classifier: Intended Audience :: Developers
Classifier: Topic :: Software Development :: Build Tools
Classifier: License :: OSI Approved :: MIT License
Classifier: Programming Language :: Python :: 3
Classifier: Programming Language :: Python :: 3.4
Classifier: Programming Language :: Python :: 3.5
Classifier: Programming Language :: Python :: 3.6
Classifier: Programming Language :: Python :: 3.7
Classifier: Programming Language :: Python :: 3.8
Classifier: Programming Language :: Python :: 3.9
Classifier: Programming Language :: Python :: 3.10
License-File: LICENSE.txt
